practicus/__init__.cpython-310-darwin.so
practicus/app.conf
practicus/app.cpython-310-darwin.so
practicus/app_conf.cpython-310-darwin.so
practicus/app_starter.cpython-310-darwin.so
practicus/app_state.cpython-310-darwin.so
practicus/cloud_app_mgr.cpython-310-darwin.so
practicus/cloud_shared.cpython-310-darwin.so
practicus/cloud_tab.cpython-310-darwin.so
practicus/cloud_threads.cpython-310-darwin.so
practicus/code_tab.cpython-310-darwin.so
practicus/deployment.cpython-310-darwin.so
practicus/dlg.cpython-310-darwin.so
practicus/dlg2.cpython-310-darwin.so
practicus/exp2_apps.cpython-310-darwin.so
practicus/exp2_conn_base.cpython-310-darwin.so
practicus/exp2_conn_base_widget.cpython-310-darwin.so
practicus/exp2_conn_dlg.cpython-310-darwin.so
practicus/exp2_conn_mgr_factory.cpython-310-darwin.so
practicus/exp2_conn_tree.cpython-310-darwin.so
practicus/exp2_def.cpython-310-darwin.so
practicus/exp2_dlg.cpython-310-darwin.so
practicus/exp2_local_file.cpython-310-darwin.so
practicus/exp2_models.cpython-310-darwin.so
practicus/exp2_models_preview.cpython-310-darwin.so
practicus/exp2_nav_base.cpython-310-darwin.so
practicus/exp2_preview.cpython-310-darwin.so
practicus/exp2_region_home_page.cpython-310-darwin.so
practicus/exp2_relational.cpython-310-darwin.so
practicus/exp2_s3.cpython-310-darwin.so
practicus/exp2_sampling_settings.cpython-310-darwin.so
practicus/exp2_shared.cpython-310-darwin.so
practicus/exp2_tab.cpython-310-darwin.so
practicus/exp2_tree_nav.cpython-310-darwin.so
practicus/exp2_tree_nav_apps.cpython-310-darwin.so
practicus/exp2_tree_nav_models.cpython-310-darwin.so
practicus/exp2_tree_nav_workflows.cpython-310-darwin.so
practicus/exp2_web_page.cpython-310-darwin.so
practicus/exp2_widget.cpython-310-darwin.so
practicus/exp2_wn_file.cpython-310-darwin.so
practicus/exp2_worker_node.cpython-310-darwin.so
practicus/exp2_workflows.cpython-310-darwin.so
practicus/file_transfer_tab.cpython-310-darwin.so
practicus/graph_tab.cpython-310-darwin.so
practicus-25.5.2.dist-info/METADATA
practicus-25.5.2.dist-info/WHEEL
practicus-25.5.2.dist-info/entry_points.txt
practicus-25.5.2.dist-info/top_level.txt
practicus-25.5.2.dist-info/RECORD
