Metadata-Version: 2.1
Name: practicus
Version: 25.5.2
Summary: Practicus AI Studio is an end-to-end Data Science and Generative AI platform.
Home-page: https://practicus.ai/
Author: Practicus AI LLC
Author-email: info@practicus.ai
Requires-Python: >=3.10
Requires-Dist: practicuscore==25.5.2
Requires-Dist: pandas==2.2.3
Requires-Dist: requests
Requires-Dist: websocket-client==1.8.0
Requires-Dist: lz4==4.4.4
Requires-Dist: pyOpenSSL
Requires-Dist: chardet==5.2.0
Requires-Dist: openpyxl
Requires-Dist: PyJWT[crypto]==2.10.1
Requires-Dist: duckdb==1.3.2
Requires-Dist: cryptography
Requires-Dist: certifi
Requires-Dist: truststore
Requires-Dist: pydantic>2
Requires-Dist: matplotlib==3.10.5
Requires-Dist: pyperclip==1.9.0
Requires-Dist: croniter<3
Requires-Dist: PyQt6==6.7.1
Requires-Dist: PyQt6-Qt6==6.7.2
Requires-Dist: PyQt6-Charts==6.7.0
Requires-Dist: PyQt6-Charts-Qt6==6.7.3
Requires-Dist: PyQt6-WebEngine==6.7.0
Requires-Dist: PyQt6-WebEngine-Qt6==6.7.3
